{
  "franchise": "Harry Potter",
  "source": "J.K. Rowling's Harry Potter series",
  "characters": [
    {"name": "Harry Potter", "description": "The Boy Who Lived, protagonist"},
    {"name": "Hermione Granger", "description": "Brilliant witch, Harry's best friend"},
    {"name": "Ron Weasley", "description": "Loyal friend, youngest Weasley son"},
    {"name": "Albus Dumbledore", "description": "Hogwarts headmaster, greatest wizard of his age"},
    {"name": "Severus Snape", "description": "Potions master, complex double agent"},
    {"name": "Lord Voldemort", "description": "Dark Lord, main antagonist"},
    {"name": "Draco Malfoy", "description": "Slytherin rival, conflicted pure-blood"},
    {"name": "Rubeus Hagrid", "description": "Half-giant groundskeeper, loyal friend"},
    {"name": "Sirius Black", "description": "Harry's godfather, wrongly imprisoned"},
    {"name": "Remus Lupin", "description": "Werewolf, Defense Against Dark Arts teacher"},
    {"name": "Neville Longbottom", "description": "Brave Gryffindor, could have been the Chosen One"},
    {"name": "Luna Lovegood", "description": "Eccentric Ravenclaw, believer in the unusual"},
    {"name": "Ginny Weasley", "description": "Fierce witch, Harry's eventual wife"},
    {"name": "Fred Weasley", "description": "Mischievous twin, joke shop owner"},
    {"name": "George Weasley", "description": "Mischievous twin, joke shop owner"},
    {"name": "Molly Weasley", "description": "Weasley matriarch, fierce mother"},
    {"name": "Arthur Weasley", "description": "Muggle-loving Ministry worker"},
    {"name": "Bellatrix Lestrange", "description": "Fanatical Death Eater, Voldemort's most loyal"},
    {"name": "Minerva McGonagall", "description": "Stern Transfiguration professor, Gryffindor head"},
    {"name": "Dobby the House Elf", "description": "Free elf, devoted to Harry"},
    {"name": "Lucius Malfoy", "description": "Aristocratic Death Eater, Draco's father"},
    {"name": "Narcissa Malfoy", "description": "Protective mother, saved Harry to find Draco"},
    {"name": "Peter Pettigrew", "description": "Cowardly traitor, Wormtail"},
    {"name": "Nymphadora Tonks", "description": "Metamorphmagus Auror, clumsy and brave"},
    {"name": "Alastor Moody", "description": "Paranoid Auror, Mad-Eye"},
    {"name": "Cedric Diggory", "description": "Hufflepuff prefect, Triwizard champion"},
    {"name": "Cho Chang", "description": "Ravenclaw seeker, Harry's first crush"},
    {"name": "Viktor Krum", "description": "Bulgarian Quidditch star, Durmstrang champion"},
    {"name": "Fleur Delacour", "description": "Part-Veela, Beauxbatons champion"},
    {"name": "Bill Weasley", "description": "Curse-breaker, eldest Weasley"},
    {"name": "Charlie Weasley", "description": "Dragon handler in Romania"},
    {"name": "Percy Weasley", "description": "Ambitious Ministry worker, estranged from family"},
    {"name": "Kreacher", "description": "Black family house-elf, initially hostile"},
    {"name": "Dolores Umbridge", "description": "Sadistic Ministry official, hated teacher"},
    {"name": "Cornelius Fudge", "description": "Incompetent Minister for Magic"},
    {"name": "Rufus Scrimgeour", "description": "War-time Minister, former Auror"},
    {"name": "Kingsley Shacklebolt", "description": "Auror, eventual Minister for Magic"},
    {"name": "Horace Slughorn", "description": "Potions master, collector of talented students"},
    {"name": "Gilderoy Lockhart", "description": "Fraud celebrity author, memory charms"},
    {"name": "Quirinus Quirrell", "description": "Nervous professor, Voldemort's host"},
    {"name": "Barty Crouch Jr", "description": "Death Eater, impersonated Moody"},
    {"name": "Barty Crouch Sr", "description": "Strict Ministry official, disowned his son"},
    {"name": "Fenrir Greyback", "description": "Savage werewolf, attacks children"},
    {"name": "Regulus Black", "description": "Reformed Death Eater, stole Horcrux"},
    {"name": "Aberforth Dumbledore", "description": "Albus's brother, Hog's Head bartender"},
    {"name": "Gellert Grindelwald", "description": "Dark wizard, Dumbledore's former friend"},
    {"name": "Tom Riddle", "description": "Young Voldemort, charming psychopath"},
    {"name": "Moaning Myrtle", "description": "Ghost in girls' bathroom, Chamber victim"},
    {"name": "Nearly Headless Nick", "description": "Gryffindor ghost, Sir Nicholas"},
    {"name": "The Bloody Baron", "description": "Slytherin ghost, Helena's killer"},
    {"name": "Helena Ravenclaw", "description": "Grey Lady, Rowena's daughter"},
    {"name": "Peeves", "description": "Poltergeist, causes chaos"},
    {"name": "Argus Filch", "description": "Bitter caretaker, Squib"},
    {"name": "Madame Pomfrey", "description": "Hogwarts matron, healer"},
    {"name": "Professor Sprout", "description": "Herbology teacher, Hufflepuff head"},
    {"name": "Professor Flitwick", "description": "Charms teacher, Ravenclaw head"},
    {"name": "Professor Trelawney", "description": "Divination teacher, made the prophecy"},
    {"name": "Firenze", "description": "Centaur Divination teacher"},
    {"name": "Lavender Brown", "description": "Ron's girlfriend, killed by Greyback"},
    {"name": "Parvati Patil", "description": "Gryffindor, Harry's Yule Ball date"},
    {"name": "Padma Patil", "description": "Ravenclaw twin, Ron's Yule Ball date"},
    {"name": "Seamus Finnigan", "description": "Irish Gryffindor, pyrotechnic tendencies"},
    {"name": "Dean Thomas", "description": "Gryffindor, Muggle-born artist"},
    {"name": "Oliver Wood", "description": "Obsessive Quidditch captain"},
    {"name": "Katie Bell", "description": "Gryffindor Chaser, cursed by necklace"},
    {"name": "Angelina Johnson", "description": "Gryffindor Chaser, Quidditch captain"},
    {"name": "Lee Jordan", "description": "Quidditch commentator, twins' friend"},
    {"name": "Colin Creevey", "description": "Harry's biggest fan, died in battle"},
    {"name": "Dennis Creevey", "description": "Colin's younger brother"},
    {"name": "Crabbe", "description": "Draco's brutish follower"},
    {"name": "Goyle", "description": "Draco's brutish follower"},
    {"name": "Pansy Parkinson", "description": "Slytherin mean girl, Draco's girlfriend"},
    {"name": "Blaise Zabini", "description": "Slytherin, handsome and aloof"},
    {"name": "Theodore Nott", "description": "Slytherin, Death Eater's son"},
    {"name": "Marcus Flint", "description": "Slytherin Quidditch captain, dirty player"},
    {"name": "Cormac McLaggen", "description": "Arrogant Gryffindor Keeper"},
    {"name": "Romilda Vane", "description": "Tried to love potion Harry"},
    {"name": "Xenophilius Lovegood", "description": "Luna's father, Quibbler editor"},
    {"name": "Mundungus Fletcher", "description": "Petty thief, Order member"},
    {"name": "Madam Rosmerta", "description": "Three Broomsticks landlady"},
    {"name": "Rita Skeeter", "description": "Unscrupulous journalist, unregistered Animagus"},
    {"name": "Stan Shunpike", "description": "Knight Bus conductor"},
    {"name": "Ernie Prang", "description": "Knight Bus driver"},
    {"name": "Madam Maxime", "description": "Beauxbatons headmistress, half-giant"},
    {"name": "Igor Karkaroff", "description": "Durmstrang headmaster, former Death Eater"},
    {"name": "Winky", "description": "Crouch family house-elf, freed and distressed"},
    {"name": "Aragog", "description": "Giant spider, Hagrid's friend"},
    {"name": "Buckbeak", "description": "Hippogriff, later called Witherwings"},
    {"name": "Fawkes", "description": "Dumbledore's phoenix"},
    {"name": "Norbert", "description": "Norwegian Ridgeback dragon, later Norberta"},
    {"name": "Hedwig", "description": "Harry's snowy owl"},
    {"name": "Crookshanks", "description": "Hermione's half-Kneazle cat"},
    {"name": "Scabbers", "description": "Ron's rat, actually Peter Pettigrew"},
    {"name": "Nagini", "description": "Voldemort's snake, Horcrux"},
    {"name": "The Sorting Hat", "description": "Sentient hat that sorts students"},
    {"name": "Griphook", "description": "Goblin, helped break into Gringotts"},
    {"name": "Ollivander", "description": "Wandmaker"},
    {"name": "Nicolas Flamel", "description": "Alchemist, created Philosopher's Stone"},
    {"name": "Petunia Dursley", "description": "Harry's aunt, magic-hating"},
    {"name": "Vernon Dursley", "description": "Harry's uncle, bullying Muggle"},
    {"name": "Dudley Dursley", "description": "Harry's cousin, eventually reformed"},
    {"name": "Aunt Marge", "description": "Vernon's sister, inflated by Harry"}
  ]
}
